vobject/__init__.py
vobject/base.py
vobject/behavior.py
vobject/change_tz.py
vobject/hcalendar.py
vobject/icalendar.py
vobject/ics_diff.py
vobject/vcard.py
vobject/win32tz.py
vobject-0.9.9.dist-info/LICENSE-2.0.txt
vobject-0.9.9.dist-info/METADATA
vobject-0.9.9.dist-info/WHEEL
vobject-0.9.9.dist-info/entry_points.txt
vobject-0.9.9.dist-info/top_level.txt
vobject-0.9.9.dist-info/zip-safe
vobject-0.9.9.dist-info/RECORD
