Metadata-Version: 1.2
Name: vobject
Version: 0.9.9
Summary: A full-featured Python package for parsing and creating iCalendar and vCard files
Home-page: UNKNOWN
Author: Jeffrey Harris
Author-email: jeffrey@osafoundation.org
Maintainer: David Arnold
Maintainer-email: davida@pobox.com
License: Apache
Project-URL: Home, http://py-vobject.github.io/
Project-URL: GitHub, https://github.com/py-vobject/vobject
Project-URL: Download, https://github.com/py-vobject/vobject/releases
Project-URL: Issues, https://github.com/py-vobject/vobject/issues
Keywords: vobject,icalendar,vcard,ics,vcs,hcalendar
Platform: any
Classifier: Development Status :: 5 - Production/Stable
Classifier:       Environment :: Console
Classifier:       Intended Audience :: Developers
Classifier:       License :: OSI Approved :: Apache Software License
Classifier:       Natural Language :: English
Classifier:       Operating System :: OS Independent
Classifier:       Programming Language :: Python
Classifier:       Programming Language :: Python :: 2.7
Classifier:       Programming Language :: Python :: 3
Classifier:       Topic :: Text Processing
